{
	"storyName": "Capitulo 6: no es tan malo como creia",
	"difficulties": "easy",
	"hideFreeplay": false,
	"weekBackground": "dad",
	"freeplayColor": [
		146,
		113,
		253
	],
	"weekBefore": "day4",
	"startUnlocked": false,
	"weekCharacters": [
		"",
		"",
		""
	],
	"songs": [
		[
			"daddy",
			"dadfx",
			[
				226,
				20,
				75
			]
		],
		[
			"daddy song",
			"dadfx",
			[
				226,
				20,
				75
			]
		],
		[
			"dad rap",
			"dadfx",
			[
				226,
				20,
				75
			]
		]
	],
	"hideStoryMode": false,
	"portrait": "dad",
	"weekName": "Custom Week",
	"hiddenUntilUnlocked": true
}