{
	"animations": [
		{
			"offsets": [
				13,
				-50
			],
			"loop": false,
			"fps": 24,
			"anim": "singLEFT",
			"indices": [],
			"name": "SKIDLEFT"
		},
		{
			"offsets": [
				18,
				-86
			],
			"loop": false,
			"fps": 24,
			"anim": "singRIGHT",
			"indices": [],
			"name": "SKIDRIGHT"
		},
		{
			"offsets": [
				-37,
				19
			],
			"loop": false,
			"fps": 24,
			"anim": "singUP",
			"indices": [],
			"name": "SKIDUP"
		},
		{
			"offsets": [
				45,
				-7
			],
			"loop": false,
			"fps": 24,
			"anim": "singDOWN",
			"indices": [],
			"name": "SKIDDOWN"
		},
		{
			"offsets": [
				-91,
				-98
			],
			"loop": false,
			"fps": 24,
			"anim": "idle",
			"indices": [],
			"name": "SKIDIDLE"
		},
		{
			"offsets": [
				-94,
				-95
			],
			"loop": false,
			"fps": 24,
			"anim": "hey",
			"indices": [],
			"name": "SKIDHEY"
		},
		{
			"loop": false,
			"offsets": [
				-49,
				-20
			],
			"anim": "laugh",
			"fps": 48,
			"name": "SKIDLAUGH",
			"indices": []
		}
	],
	"no_antialiasing": false,
	"image": "characters/SKIDBSIDE",
	"position": [
		0,
		170
	],
	"healthicon": "icon-huefano",
	"flip_x": false,
	"healthbar_colors": [
		189,
		81,
		0
	],
	"camera_position": [
		0,
		70
	],
	"sing_duration": 4,
	"scale": 1
}